.coveragerc
.editorconfig
.gitignore
.travis.yml
AUTHORS.rst
CONTRIBUTING.rst
HISTORY.rst
LICENSE
MANIFEST.in
Makefile
README.rst
manage.py
requirements.txt
requirements_dev.txt
requirements_test.txt
runtests.py
setup.cfg
setup.py
tox.ini
.github/ISSUE_TEMPLATE.md
django_like_lookup.egg-info/PKG-INFO
django_like_lookup.egg-info/SOURCES.txt
django_like_lookup.egg-info/dependency_links.txt
django_like_lookup.egg-info/not-zip-safe
django_like_lookup.egg-info/top_level.txt
docs/Makefile
docs/authors.rst
docs/conf.py
docs/contributing.rst
docs/history.rst
docs/index.rst
docs/installation.rst
docs/make.bat
docs/readme.rst
docs/usage.rst
like_lookup/__init__.py
tests/README.md
tests/__init__.py
tests/requirements.txt
tests/settings.py
tests/test_models.py
tests/urls.py