Metadata-Version: 1.1
Name: django-like-lookup
Version: 0.1.0
Summary: PostgreSQL LIKE lookup functionality for Django. Django does contain __startswith, __endswith and __contains lookups, but all of them does escape "%" and "_" wildcard characters. The `__like` lookup is often faster, than the `__regex` lookup, so it can be used in cases when conditions are simple enough.
Home-page: https://github.com/PetrDlouhy/django-like-lookup
Author: Petr Dlouhý
Author-email: petr.dlouhy@email.cz
License: MIT
Keywords: django-like-lookup
Platform: UNKNOWN
Classifier: Development Status :: 3 - Alpha
Classifier: Framework :: Django :: 1.11
Classifier: Framework :: Django :: 2.1
Classifier: Intended Audience :: Developers
Classifier: License :: OSI Approved :: BSD License
Classifier: Natural Language :: English
Classifier: Programming Language :: Python :: 2
Classifier: Programming Language :: Python :: 2.7
Classifier: Programming Language :: Python :: 3
Classifier: Programming Language :: Python :: 3.5
Classifier: Programming Language :: Python :: 3.6
